finbourne_insights/__init__.py
finbourne_insights/__version__.py
finbourne_insights/api_client.py
finbourne_insights/configuration.py
finbourne_insights/exceptions.py
finbourne_insights/rest.py
finbourne_insights/api/__init__.py
finbourne_insights/api/access_evaluations_api.py
finbourne_insights/api/application_metadata_api.py
finbourne_insights/api/auditing_api.py
finbourne_insights/api/requests_api.py
finbourne_insights/api/vendor_logs_api.py
finbourne_insights/models/__init__.py
finbourne_insights/models/access_controlled_action.py
finbourne_insights/models/access_controlled_resource.py
finbourne_insights/models/access_evaluation_log.py
finbourne_insights/models/action_id.py
finbourne_insights/models/audit_data.py
finbourne_insights/models/audit_data_summary.py
finbourne_insights/models/audit_entry.py
finbourne_insights/models/audit_entry_note.py
finbourne_insights/models/audit_process.py
finbourne_insights/models/audit_process_summary.py
finbourne_insights/models/bucket.py
finbourne_insights/models/create_audit_entry.py
finbourne_insights/models/histogram.py
finbourne_insights/models/id_selector_definition.py
finbourne_insights/models/identifier_part_schema.py
finbourne_insights/models/link.py
finbourne_insights/models/lusid_problem_details.py
finbourne_insights/models/lusid_validation_problem_details.py
finbourne_insights/models/problem_details.py
finbourne_insights/models/request.py
finbourne_insights/models/request_log.py
finbourne_insights/models/resource.py
finbourne_insights/models/resource_list_of_access_controlled_resource.py
finbourne_insights/models/resource_list_of_audit_process_summary.py
finbourne_insights/models/resource_list_with_histogram_of_access_evaluation_log.py
finbourne_insights/models/resource_list_with_histogram_of_request_log.py
finbourne_insights/models/resource_list_with_histogram_of_vendor_log.py
finbourne_insights/models/response.py
finbourne_insights/models/scrollable_collection_of_audit_entry.py
finbourne_insights_sdk_preview-0.0.807.dist-info/METADATA
finbourne_insights_sdk_preview-0.0.807.dist-info/WHEEL
finbourne_insights_sdk_preview-0.0.807.dist-info/top_level.txt
finbourne_insights_sdk_preview-0.0.807.dist-info/RECORD
