Metadata-Version: 2.1
Name: finbourne-insights-sdk-preview
Version: 0.0.807
Summary: Python SDK for FINBOURNE Insights API
Home-page: https://github.com/finbourne/finbourne-insights-sdk-python
Author: FINBOURNE Technology
Author-email: engineering@finbourne.com
License: MIT
Keywords: OpenAPI,FINBOURNE,LUSID,Insights API
Platform: UNKNOWN
Requires-Dist: urllib3 (>=1.15)
Requires-Dist: six (>=1.10)
Requires-Dist: certifi (>=14.05.14)
Requires-Dist: python-dateutil (>=2.5.3)
Requires-Dist: urllib3 (>=1.15.1)
Requires-Dist: requests (>=2.21.0)
Requires-Dist: finbourne-sdk-utilities (>=0.0.10)
